{
  "project_info": {
    "project_number": "652403640384",
    "project_id": "stocktrack-734ec",
    "storage_bucket": "stocktrack-734ec.firebasestorage.app"
  },
  "client": [
    {
      "client_info": {
        "mobilesdk_app_id": "1:652403640384:android:795da4dbf5aa3e494677a5",
        "android_client_info": {
          "package_name": "com.stocktrack.app"
        }
      },
      "oauth_client": [
        {
          "client_id": "652403640384-7qs8fq330h10ugb49mt3d8e7gsk95nkp.apps.googleusercontent.com",
          "client_type": 1,
          "android_info": {
            "package_name": "com.stocktrack.app",
            "certificate_hash": "ed09b101e0813bb06b123cd1b539ef9479e14326"
          }
        },
        {
          "client_id": "652403640384-73l7hrbik9s5e2u4o06uinvhqvjcueqj.apps.googleusercontent.com",
          "client_type": 3
        }
      ],
      "api_key": [
        {
          "current_key": "AIzaSyDbpHqJC_UrFm-3T7CtGoF9o3DGeB5E7fY"
        }
      ],
      "services": {
        "appinvite_service": {
          "other_platform_oauth_client": [
            {
              "client_id": "652403640384-73l7hrbik9s5e2u4o06uinvhqvjcueqj.apps.googleusercontent.com",
              "client_type": 3
            }
          ]
        }
      }
    }
  ],
  "configuration_version": "1"
}